hadmin/__init__.py
hadmin/mixins.py
hadmin/utils.py
hadmin-1.2.1.dist-info/LICENSE
hadmin-1.2.1.dist-info/METADATA
hadmin-1.2.1.dist-info/WHEEL
hadmin-1.2.1.dist-info/top_level.txt
hadmin-1.2.1.dist-info/RECORD
