Metadata-Version: 2.1
Name: hadmin
Version: 1.2.1
Summary: 针对自动化给予前端配置文件的DRF封装
Home-page: https://github.com/spirits001/python-HAdmin
Author: 代码厨子
Author-email: 15755153@qq.com
Classifier: Programming Language :: Python :: 3
Classifier: License :: OSI Approved :: MIT License
Classifier: Operating System :: OS Independent
Requires-Python: >=3
License-File: LICENSE
Requires-Dist: djangorestframework
